g3t/__init__.py
g3t/__version__.py
g3t/composite_properties.py
g3t/csv_to_sql.py
g3t/g3read.py
g3t/matcha.py
g3t/plotto.py
g3t/pp.py
g3t/pp_schema.py
g3t/runjob.py
g3t/subfind_to_sql.py
g3t/test_beta.py
g3t/stable/c2pap_batch.py
g3t/stable/convert_gadget_to_hdf5.py
g3t/stable/convert_gadget_to_hdf5_for_splotchweb.py
g3t/stable/g3read.py
g3t/stable/pp.py
g3t/stable/test_box1_lib.py
g3t/stable/test_lib.py
g3t-0.1.dist-info/METADATA
g3t-0.1.dist-info/WHEEL
g3t-0.1.dist-info/top_level.txt
g3t-0.1.dist-info/RECORD
