Metadata-Version: 2.1
Name: g3t
Version: 0.1
Summary: Gadget3 read routines & other scripts.
Author-email: Kyle Oman <kyle.a.oman@durham.ac.uk>, Antonio Ragagnin <antonio.ragagnin@inaf.it>
Project-URL: Homepage, https://github.com/kyleaoman/g3t
Project-URL: Bug Tracker, https://github.com/kyleaoman/g3t/issues
Classifier: Programming Language :: Python :: 3
Classifier: License :: OSI Approved :: GNU General Public License v3 (GPLv3)
Classifier: Operating System :: OS Independent
Requires-Python: >=3.7
Requires-Dist: numpy
Requires-Dist: h5py
